Metadata-Version: 1.1
Name: snnm
Version: 0.2.9
Summary: Naming helper
Home-page: https://github.com/ewilazarus/snnm
Author: Gabriel Lima
Author-email: gvclima@gmail.com
License: MIT
Download-URL: https://github.com/ewilazarus/snnm/tarball/0.2.9
Keywords: synonym
Platform: UNKNOWN
